kadia/__init__.py
kadia/chains/__init__.py
kadia/chains/base.py
kadia/chains/map_reduce.py
kadia/cli.py
kadia/configs/__init__.py
kadia/configs/_generator.py
kadia/data_source/__init__.py
kadia/data_source/base.py
kadia/data_source/geck_data_source.py
kadia/document_chunker.py
kadia/embedder.py
kadia/exceptions.py
kadia/kadia_ai.py
kadia/llm_manager.py
kadia/model.py
kadia/prompts/__init__.py
kadia/prompts/base.py
kadia/text_splitters.py
kadia/vector_storage/__init__.py
kadia/vector_storage/base.py
kadia/vector_storage/qdrant.py
kadia-1.0.10.dist-info/METADATA
kadia-1.0.10.dist-info/WHEEL
kadia-1.0.10.dist-info/entry_points.txt
kadia-1.0.10.dist-info/RECORD
