Metadata-Version: 2.1
Name: kadia
Version: 1.0.10
Summary: 
Author: Pasha Podolsky
Author-email: ppodolsky@me.com
Requires-Python: >=3.9,<3.13
Classifier: Programming Language :: Python :: 3
Classifier: Programming Language :: Python :: 3.9
Classifier: Programming Language :: Python :: 3.10
Classifier: Programming Language :: Python :: 3.11
Classifier: Programming Language :: Python :: 3.12
Requires-Dist: aiokit (>=1.3.2,<2.0.0)
Requires-Dist: beautifulsoup4 (>=4.12.2,<5.0.0)
Requires-Dist: confuse (>=2.0.1,<3.0.0)
Requires-Dist: ctransformers (>=0.2.27,<0.3.0)
Requires-Dist: flagembedding (>=1.1.6,<2.0.0)
Requires-Dist: izihawa-configurator (>=1.0.4,<2.0.0)
Requires-Dist: izihawa-textutils (>=1.0.23,<2.0.0)
Requires-Dist: izihawa-utils (>=1.2.1,<2.0.0)
Requires-Dist: keybert (>=0.8.3,<0.9.0)
Requires-Dist: langchain (>=0.0.341,<0.0.342)
Requires-Dist: lazy (>=1.6,<2.0)
Requires-Dist: lxml (>=4.9.3,<5.0.0)
Requires-Dist: orjson (>=3.9.10,<4.0.0)
Requires-Dist: pypdf (>=3.17.1,<4.0.0)
Requires-Dist: pyyaml (>=6.0.1,<7.0.0)
Requires-Dist: qdrant-client (>=1.6.9,<2.0.0)
Requires-Dist: stc-geck (>=1.8.38,<2.0.0)
Requires-Dist: tiktoken (>=0.5.1,<0.6.0)
Requires-Dist: unstructured (>=0.11.0,<0.12.0)
